machin/__init__.py
machin/auto/__init__.py
machin/auto/__main__.py
machin/auto/config.py
machin/auto/dataset.py
machin/auto/launcher.py
machin/auto/pl_logger.py
machin/auto/pl_plugin.py
machin/auto/envs/__init__.py
machin/auto/envs/openai_gym.py
machin/env/__init__.py
machin/env/utils/__init__.py
machin/env/utils/openai_gym.py
machin/env/wrappers/__init__.py
machin/env/wrappers/base.py
machin/env/wrappers/openai_gym.py
machin/frame/__init__.py
machin/frame/transition.py
machin/frame/algorithms/__init__.py
machin/frame/algorithms/a2c.py
machin/frame/algorithms/a3c.py
machin/frame/algorithms/apex.py
machin/frame/algorithms/ars.py
machin/frame/algorithms/base.py
machin/frame/algorithms/ddpg.py
machin/frame/algorithms/ddpg_per.py
machin/frame/algorithms/dqn.py
machin/frame/algorithms/dqn_per.py
machin/frame/algorithms/gail.py
machin/frame/algorithms/hddpg.py
machin/frame/algorithms/impala.py
machin/frame/algorithms/maddpg.py
machin/frame/algorithms/ppo.py
machin/frame/algorithms/rainbow.py
machin/frame/algorithms/sac.py
machin/frame/algorithms/td3.py
machin/frame/algorithms/trpo.py
machin/frame/algorithms/utils.py
machin/frame/buffers/__init__.py
machin/frame/buffers/buffer.py
machin/frame/buffers/buffer_d.py
machin/frame/buffers/prioritized_buffer.py
machin/frame/buffers/prioritized_buffer_d.py
machin/frame/helpers/__init__.py
machin/frame/helpers/servers.py
machin/frame/noise/__init__.py
machin/frame/noise/action_space_noise.py
machin/frame/noise/generator.py
machin/frame/noise/param_space_noise.py
machin/model/__init__.py
machin/model/algorithms/__init__.py
machin/model/algorithms/trpo.py
machin/model/nets/__init__.py
machin/model/nets/base.py
machin/model/nets/resnet.py
machin/parallel/__init__.py
machin/parallel/assigner.py
machin/parallel/event.py
machin/parallel/exception.py
machin/parallel/pickle.py
machin/parallel/pool.py
machin/parallel/process.py
machin/parallel/queue.py
machin/parallel/thread.py
machin/parallel/util.py
machin-0.4.2.dist-info/LICENSE
machin-0.4.2.dist-info/METADATA
machin-0.4.2.dist-info/WHEEL
machin-0.4.2.dist-info/top_level.txt
machin-0.4.2.dist-info/RECORD
