Metadata-Version: 2.1
Name: machin
Version: 0.4.2
Summary: Reinforcement learning library
Home-page: https://github.com/iffiX/machin
Author: Iffi
Author-email: iffi@mail.beyond-infinity.com
License: MIT
Platform: UNKNOWN
Classifier: Development Status :: 4 - Beta
Classifier: Intended Audience :: Developers
Classifier: Intended Audience :: Science/Research
Classifier: Topic :: Scientific/Engineering :: Artificial Intelligence
Classifier: Topic :: Software Development :: Libraries :: Python Modules
Classifier: License :: OSI Approved :: MIT License
Classifier: Programming Language :: Python :: 3.6
Classifier: Programming Language :: Python :: 3.7
Classifier: Programming Language :: Python :: 3.8
Requires-Python: >=3.5
Requires-Dist: gym
Requires-Dist: psutil
Requires-Dist: numpy
Requires-Dist: torch (>=1.6.0)
Requires-Dist: pytorch-lightning (>=1.2.0)
Requires-Dist: torchviz
Requires-Dist: moviepy
Requires-Dist: matplotlib
Requires-Dist: colorlog
Requires-Dist: dill
Requires-Dist: GPUtil
Requires-Dist: Pillow
Requires-Dist: tensorboardX
